{"type": "FeatureCollection", "features": [{"type": "Feature", "geometry": {"type": "Point", "coordinates": [88.36304, 22.56263]}, "properties": {"source_label": "Calcutta", "geonames_label": "Kolkata", "url": "https://www.geonames.org/1275004", "sentence_idx": 1765}}, {"type": "Feature", "geometry": {"type": "Point", "coordinates": [88.36304, 22.56263]}, "properties": {"source_label": "Calcutta", "geonames_label": "Kolkata", "url": "https://www.geonames.org/1275004", "sentence_idx": 1770}}, {"type": "Feature", "geometry": {"type": "Point", "coordinates": [88.36304, 22.56263]}, "properties": {"source_label": "Calcutta", "geonames_label": "Kolkata", "url": "https://www.geonames.org/1275004", "sentence_idx": 1771}}, {"type": "Feature", "geometry": {"type": "Point", "coordinates": [88.36304, 22.56263]}, "properties": {"source_label": "Calcutta", "geonames_label": "Kolkata", "url": "https://www.geonames.org/1275004", "sentence_idx": 1776}}, {"type": "Feature", "geometry": {"type": "Point", "coordinates": [88.36304, 22.56263]}, "properties": {"source_label": "Calcutta", "geonames_label": "Kolkata", "url": "https://www.geonames.org/1275004", "sentence_idx": 1790}}]}