{
    "type": "FeatureCollection",
    "features": [
        {
            "type": "Feature",
            "geometry": {
                "type": "Point",
                "coordinates": [
                    72.88261,
                    19.07283
                ]
            },
            "properties": {
                "source_label": "Bombay",
                "geonames_label": "Mumbai",
                "url": "https://www.geonames.org/1275339",
                "sentence_idx": "604"
            }
        },
        {
            "type": "Feature",
            "geometry": {
                "type": "Point",
                "coordinates": [
                    89.29688,
                    29.84064
                ]
            },
            "properties": {
                "source_label": "Asien",
                "geonames_label": "Asia",
                "url": "https://www.geonames.org/6255147",
                "sentence_idx": "607"
            }
        },
        {
            "type": "Feature",
            "geometry": {
                "type": "Point",
                "coordinates": [
                    79.0,
                    22.0
                ]
            },
            "properties": {
                "source_label": "Indien",
                "geonames_label": "India",
                "url": "https://www.geonames.org/1269750",
                "sentence_idx": "608"
            }
        },
        {
            "type": "Feature",
            "geometry": {
                "type": "Point",
                "coordinates": [
                    79.0,
                    22.0
                ]
            },
            "properties": {
                "source_label": "Indien",
                "geonames_label": "India",
                "url": "https://www.geonames.org/1269750",
                "sentence_idx": "614"
            }
        }
    ]
}