{
    "type": "FeatureCollection",
    "features": [
        {
            "type": "Feature",
            "geometry": {
                "type": "Point",
                "coordinates": [
                    114.16667,
                    22.25
                ]
            },
            "properties": {
                "source_label": "Hongkong",
                "geonames_label": "Hong Kong",
                "url": "https://www.geonames.org/1819729",
                "sentence_idx": 2445
            }
        },
        {
            "type": "Feature",
            "geometry": {
                "type": "Point",
                "coordinates": [
                    114.16667,
                    22.25
                ]
            },
            "properties": {
                "source_label": "Hongkong",
                "geonames_label": "Hong Kong",
                "url": "https://www.geonames.org/1819729",
                "sentence_idx": 2447
            }
        },
        {
            "type": "Feature",
            "geometry": {
                "type": "Point",
                "coordinates": [
                    114.16667,
                    22.25
                ]
            },
            "properties": {
                "source_label": "Hongkong",
                "geonames_label": "Hong Kong",
                "url": "https://www.geonames.org/1819729",
                "sentence_idx": 2451
            }
        },
        {
            "type": "Feature",
            "geometry": {
                "type": "Point",
                "coordinates": [
                    113.55972,
                    22.15778
                ]
            },
            "properties": {
                "source_label": "Macao",
                "geonames_label": "Macao",
                "url": "https://www.geonames.org/1821274",
                "sentence_idx": 2461
            }
        }
    ]
}