{"type": "FeatureCollection", "features": [{"type": "Feature", "geometry": {"type": "Point", "coordinates": [114.16667, 22.25]}, "properties": {"source_label": "Hongkong", "geonames_label": "Hong Kong", "url": "https://www.geonames.org/1819729", "sentence_idx": 1951}}, {"type": "Feature", "geometry": {"type": "Point", "coordinates": [114.16667, 22.25]}, "properties": {"source_label": "Hongkong", "geonames_label": "Hong Kong", "url": "https://www.geonames.org/1819729", "sentence_idx": 1958}}, {"type": "Feature", "geometry": {"type": "Point", "coordinates": [114.16667, 22.25]}, "properties": {"source_label": "Hongkong", "geonames_label": "Hong Kong", "url": "https://www.geonames.org/1819729", "sentence_idx": 1965}}, {"type": "Feature", "geometry": {"type": "Point", "coordinates": [114.16667, 22.25]}, "properties": {"source_label": "Hongkong", "geonames_label": "Hong Kong", "url": "https://www.geonames.org/1819729", "sentence_idx": 1969}}]}