{
    "type": "FeatureCollection",
    "features": [
        {
            "type": "Feature",
            "geometry": {
                "type": "Point",
                "coordinates": [
                    82.0,
                    24.61667
                ]
            },
            "properties": {
                "source_label": "Vindhiagebirges",
                "geonames_label": "Vindhya Range",
                "url": "https://www.geonames.org/1253158",
                "sentence_idx": 1258
            }
        },
        {
            "type": "Feature",
            "geometry": {
                "type": "Point",
                "coordinates": [
                    81.88385,
                    25.42012
                ]
            },
            "properties": {
                "source_label": "Allahabad",
                "geonames_label": "Prayagraj",
                "url": "https://www.geonames.org/1278994",
                "sentence_idx": 1262
            }
        },
        {
            "type": "Feature",
            "geometry": {
                "type": "Point",
                "coordinates": [
                    82.0,
                    24.61667
                ]
            },
            "properties": {
                "source_label": "Vindhia",
                "geonames_label": "Vindhya Range",
                "url": "https://www.geonames.org/1253158",
                "sentence_idx": 1270
            }
        },
        {
            "type": "Feature",
            "geometry": {
                "type": "Point",
                "coordinates": [
                    81.88385,
                    25.42012
                ]
            },
            "properties": {
                "source_label": "Allahabad",
                "geonames_label": "Prayagraj",
                "url": "https://www.geonames.org/1278994",
                "sentence_idx": 1271
            }
        },
        {
            "type": "Feature",
            "geometry": {
                "type": "Point",
                "coordinates": [
                    81.88385,
                    25.42012
                ]
            },
            "properties": {
                "source_label": "Allahabad",
                "geonames_label": "Prayagraj",
                "url": "https://www.geonames.org/1278994",
                "sentence_idx": 1284
            }
        },
        {
            "type": "Feature",
            "geometry": {
                "type": "Point",
                "coordinates": [
                    82.0,
                    24.61667
                ]
            },
            "properties": {
                "source_label": "Vindhia",
                "geonames_label": "Vindhya Range",
                "url": "https://www.geonames.org/1253158",
                "sentence_idx": 1285
            }
        },
        {
            "type": "Feature",
            "geometry": {
                "type": "Point",
                "coordinates": [
                    81.88385,
                    25.42012
                ]
            },
            "properties": {
                "source_label": "Allahabad",
                "geonames_label": "Prayagraj",
                "url": "https://www.geonames.org/1278994",
                "sentence_idx": 1288
            }
        },
        {
            "type": "Feature",
            "geometry": {
                "type": "Point",
                "coordinates": [
                    84.14906,
                    28.59743
                ]
            },
            "properties": {
                "source_label": "Pisang",
                "geonames_label": "Pisang Peak",
                "url": "https://www.geonames.org/6941682",
                "sentence_idx": 1289
            }
        }
    ]
}