{"type": "FeatureCollection", "features": [{"type": "Feature", "geometry": {"type": "Point", "coordinates": [11.5, 48.5]}, "properties": {"source_label": "bayern", "sentence_idx": 1868}}, {"type": "Feature", "geometry": {"type": "Point", "coordinates": [10.5, 51.5]}, "properties": {"source_label": "deutschland", "sentence_idx": 1884}}, {"type": "Feature", "geometry": {"type": "Point", "coordinates": [9.14062, 48.69096]}, "properties": {"source_label": "europa", "sentence_idx": 1885}}, {"type": "Feature", "geometry": {"type": "Point", "coordinates": [16.55083, 48.20278]}, "properties": {"source_label": "enzersdorf", "sentence_idx": 1893}}, {"type": "Feature", "geometry": {"type": "Point", "coordinates": [16.35607, 48.06833]}, "properties": {"source_label": "laxenburg", "sentence_idx": 1894}}, {"type": "Feature", "geometry": {"type": "Point", "coordinates": [11.24626, 43.77925]}, "properties": {"source_label": "florenz", "sentence_idx": 1898}}]}