{
    "type": "FeatureCollection",
    "features": [
        {
            "type": "Feature",
            "geometry": {
                "type": "Point",
                "coordinates": [
                    13.39658,
                    52.52313
                ]
            },
            "properties": {
                "source_label": "monbijou",
                "geonames_label": "Monbijou Park",
                "url": "https://www.geonames.org/12061014",
                "sentence_idx": "2159"
            }
        },
        {
            "type": "Feature",
            "geometry": {
                "type": "Point",
                "coordinates": [
                    13.39658,
                    52.52313
                ]
            },
            "properties": {
                "source_label": "monbijou",
                "geonames_label": "Monbijou Park",
                "url": "https://www.geonames.org/12061014",
                "sentence_idx": "2160"
            }
        },
        {
            "type": "Feature",
            "geometry": {
                "type": "Point",
                "coordinates": [
                    16.69732,
                    47.60435
                ]
            },
            "properties": {
                "source_label": "zinkendorf",
                "geonames_label": "Nagycenk",
                "url": "https://www.geonames.org/3047781",
                "sentence_idx": "2175"
            }
        }
    ]
}