{
    "type": "FeatureCollection",
    "features": [
        {
            "type": "Feature",
            "geometry": {
                "type": "Point",
                "coordinates": [
                    42.69093,
                    15.70309
                ]
            },
            "properties": {
                "source_label": "loheia",
                "geonames_label": "Al Lu\u1e29ayyah",
                "url": "https://www.geonames.org/79050",
                "sentence_idx": "6205"
            }
        },
        {
            "type": "Feature",
            "geometry": {
                "type": "Point",
                "coordinates": [
                    42.95452,
                    14.79781
                ]
            },
            "properties": {
                "source_label": "hodeida",
                "geonames_label": "Al Hudaydah",
                "url": "https://www.geonames.org/79415",
                "sentence_idx": "6221"
            }
        },
        {
            "type": "Feature",
            "geometry": {
                "type": "Point",
                "coordinates": [
                    42.69093,
                    15.70309
                ]
            },
            "properties": {
                "source_label": "loheia",
                "geonames_label": "Al Lu\u1e29ayyah",
                "url": "https://www.geonames.org/79050",
                "sentence_idx": "6221"
            }
        },
        {
            "type": "Feature",
            "geometry": {
                "type": "Point",
                "coordinates": [
                    42.69093,
                    15.70309
                ]
            },
            "properties": {
                "source_label": "loheia",
                "geonames_label": "Al Lu\u1e29ayyah",
                "url": "https://www.geonames.org/79050",
                "sentence_idx": "6223"
            }
        },
        {
            "type": "Feature",
            "geometry": {
                "type": "Point",
                "coordinates": [
                    42.69093,
                    15.70309
                ]
            },
            "properties": {
                "source_label": "loheia",
                "geonames_label": "Al Lu\u1e29ayyah",
                "url": "https://www.geonames.org/79050",
                "sentence_idx": "6239"
            }
        },
        {
            "type": "Feature",
            "geometry": {
                "type": "Point",
                "coordinates": [
                    45.0,
                    25.0
                ]
            },
            "properties": {
                "source_label": "arabien",
                "geonames_label": "Saudi Arabia",
                "url": "https://www.geonames.org/102358",
                "sentence_idx": "6243"
            }
        }
    ]
}