{
    "type": "FeatureCollection",
    "features": [
        {
            "type": "Feature",
            "geometry": {
                "type": "Point",
                "coordinates": [
                    12.56553,
                    55.67594
                ]
            },
            "properties": {
                "source_label": "kopenhagen",
                "geonames_label": "Copenhagen",
                "url": "https://www.geonames.org/2618425",
                "sentence_idx": "9464"
            }
        },
        {
            "type": "Feature",
            "geometry": {
                "type": "Point",
                "coordinates": [
                    12.56553,
                    55.67594
                ]
            },
            "properties": {
                "source_label": "kopenhagen",
                "geonames_label": "Copenhagen",
                "url": "https://www.geonames.org/2618425",
                "sentence_idx": "9466"
            }
        },
        {
            "type": "Feature",
            "geometry": {
                "type": "Point",
                "coordinates": [
                    10.0,
                    56.0
                ]
            },
            "properties": {
                "source_label": "daenemark",
                "geonames_label": "Denmark",
                "url": "https://www.geonames.org/2623032",
                "sentence_idx": "9466"
            }
        },
        {
            "type": "Feature",
            "geometry": {
                "type": "Point",
                "coordinates": [
                    12.56553,
                    55.67594
                ]
            },
            "properties": {
                "source_label": "kopenhagen",
                "geonames_label": "Copenhagen",
                "url": "https://www.geonames.org/2618425",
                "sentence_idx": "9471"
            }
        },
        {
            "type": "Feature",
            "geometry": {
                "type": "Point",
                "coordinates": [
                    12.56553,
                    55.67594
                ]
            },
            "properties": {
                "source_label": "kopenhagen",
                "geonames_label": "Copenhagen",
                "url": "https://www.geonames.org/2618425",
                "sentence_idx": "9472"
            }
        },
        {
            "type": "Feature",
            "geometry": {
                "type": "Point",
                "coordinates": [
                    12.56553,
                    55.67594
                ]
            },
            "properties": {
                "source_label": "kopenhagen",
                "geonames_label": "Copenhagen",
                "url": "https://www.geonames.org/2618425",
                "sentence_idx": "9473"
            }
        },
        {
            "type": "Feature",
            "geometry": {
                "type": "Point",
                "coordinates": [
                    12.56553,
                    55.67594
                ]
            },
            "properties": {
                "source_label": "kopenhagen",
                "geonames_label": "Copenhagen",
                "url": "https://www.geonames.org/2618425",
                "sentence_idx": "9474"
            }
        },
        {
            "type": "Feature",
            "geometry": {
                "type": "Point",
                "coordinates": [
                    12.56553,
                    55.67594
                ]
            },
            "properties": {
                "source_label": "kopenhagen",
                "geonames_label": "Copenhagen",
                "url": "https://www.geonames.org/2618425",
                "sentence_idx": "9476"
            }
        },
        {
            "type": "Feature",
            "geometry": {
                "type": "Point",
                "coordinates": [
                    12.56553,
                    55.67594
                ]
            },
            "properties": {
                "source_label": "kopenhagen",
                "geonames_label": "Copenhagen",
                "url": "https://www.geonames.org/2618425",
                "sentence_idx": "9476"
            }
        }
    ]
}