{
    "type": "FeatureCollection",
    "features": [
        {
            "type": "Feature",
            "geometry": {
                "type": "Point",
                "coordinates": [
                    42.39623,
                    12.46463
                ]
            },
            "properties": {
                "source_label": "musa",
                "geonames_label": "Musa \u0100l\u012b Terara",
                "url": "https://www.geonames.org/221593",
                "sentence_idx": "7162"
            }
        },
        {
            "type": "Feature",
            "geometry": {
                "type": "Point",
                "coordinates": [
                    42.39623,
                    12.46463
                ]
            },
            "properties": {
                "source_label": "musa",
                "geonames_label": "Musa \u0100l\u012b Terara",
                "url": "https://www.geonames.org/221593",
                "sentence_idx": "7165"
            }
        },
        {
            "type": "Feature",
            "geometry": {
                "type": "Point",
                "coordinates": [
                    42.39623,
                    12.46463
                ]
            },
            "properties": {
                "source_label": "musa",
                "geonames_label": "Musa \u0100l\u012b Terara",
                "url": "https://www.geonames.org/221593",
                "sentence_idx": "7177"
            }
        },
        {
            "type": "Feature",
            "geometry": {
                "type": "Point",
                "coordinates": [
                    32.18333,
                    12.35
                ]
            },
            "properties": {
                "source_label": "marabba",
                "geonames_label": "Marabba",
                "url": "https://www.geonames.org/370510",
                "sentence_idx": "7180"
            }
        }
    ]
}