{"type": "FeatureCollection", "features": [{"type": "Feature", "geometry": {"type": "Point", "coordinates": [-100.54688, 46.07323]}, "properties": {"source_label": "amerika", "geonames_label": "North America", "url": "https://www.geonames.org/6255149", "sentence_idx": 2238}}, {"type": "Feature", "geometry": {"type": "Point", "coordinates": [-98.5, 39.76]}, "properties": {"source_label": "vereinigten staaten von amerika", "geonames_label": "United States", "url": "https://www.geonames.org/6252001", "sentence_idx": 2242}}, {"type": "Feature", "geometry": {"type": "Point", "coordinates": [-98.5, 39.76]}, "properties": {"source_label": "vereinigten staaten von nord amerika", "geonames_label": "United States", "url": "https://www.geonames.org/6252001", "sentence_idx": 2244}}, {"type": "Feature", "geometry": {"type": "Point", "coordinates": [-98.5, 39.76]}, "properties": {"source_label": "vereinigten staaten", "geonames_label": "United States", "url": "https://www.geonames.org/6252001", "sentence_idx": 2249}}, {"type": "Feature", "geometry": {"type": "Point", "coordinates": [-100.54688, 46.07323]}, "properties": {"source_label": "nordamerika", "geonames_label": "North America", "url": "https://www.geonames.org/6255149", "sentence_idx": 2256}}, {"type": "Feature", "geometry": {"type": "Point", "coordinates": [-100.54688, 46.07323]}, "properties": {"source_label": "nordamerika", "geonames_label": "North America", "url": "https://www.geonames.org/6255149", "sentence_idx": 2261}}, {"type": "Feature", "geometry": {"type": "Point", "coordinates": [-98.5, 39.76]}, "properties": {"source_label": "vereinigten staaten", "geonames_label": "United States", "url": "https://www.geonames.org/6252001", "sentence_idx": 2275}}, {"type": "Feature", "geometry": {"type": "Point", "coordinates": [-100.54688, 46.07323]}, "properties": {"source_label": "amerika", "geonames_label": "North America", "url": "https://www.geonames.org/6255149", "sentence_idx": 2277}}, {"type": "Feature", "geometry": {"type": "Point", "coordinates": [-98.5, 39.76]}, "properties": {"source_label": "vereinigten staaten", "geonames_label": "United States", "url": "https://www.geonames.org/6252001", "sentence_idx": 2283}}, {"type": "Feature", "geometry": {"type": "Point", "coordinates": [-100.54688, 46.07323]}, "properties": {"source_label": "nord amerika", "geonames_label": "North America", "url": "https://www.geonames.org/6255149", "sentence_idx": 2297}}, {"type": "Feature", "geometry": {"type": "Point", "coordinates": [-98.5, 39.76]}, "properties": {"source_label": "vereinigten staaten von nord amerika", "geonames_label": "United States", "url": "https://www.geonames.org/6252001", "sentence_idx": 2297}}, {"type": "Feature", "geometry": {"type": "Point", "coordinates": [-98.5, 39.76]}, "properties": {"source_label": "vereinigten staaten von nord amerika", "geonames_label": "United States", "url": "https://www.geonames.org/6252001", "sentence_idx": 2298}}, {"type": "Feature", "geometry": {"type": "Point", "coordinates": [-98.5, 39.76]}, "properties": {"source_label": "vereinigten staaten", "geonames_label": "United States", "url": "https://www.geonames.org/6252001", "sentence_idx": 2298}}, {"type": "Feature", "geometry": {"type": "Point", "coordinates": [-98.5, 39.76]}, "properties": {"source_label": "vereinigten staaten von nord amerika", "geonames_label": "United States", "url": "https://www.geonames.org/6252001", "sentence_idx": 2313}}]}