{"type": "FeatureCollection", "features": [{"type": "Feature", "geometry": {"type": "Point", "coordinates": [-2.0, 54.0]}, "properties": {"source_label": "grossbritannien", "sentence_idx": 739}}, {"type": "Feature", "geometry": {"type": "Point", "coordinates": [-1.89983, 52.48142]}, "properties": {"source_label": "birmingham", "sentence_idx": 742}}, {"type": "Feature", "geometry": {"type": "Point", "coordinates": [-2.0, 54.0]}, "properties": {"source_label": "grossbritannien", "sentence_idx": 743}}]}