{"type": "FeatureCollection", "features": [{"type": "Feature", "geometry": {"type": "Point", "coordinates": [2.0, 46.0]}, "properties": {"source_label": "frankreich", "sentence_idx": 1417}}, {"type": "Feature", "geometry": {"type": "Point", "coordinates": [2.0, 46.0]}, "properties": {"source_label": "frankreich", "sentence_idx": 1419}}, {"type": "Feature", "geometry": {"type": "Point", "coordinates": [2.13424, 48.80359]}, "properties": {"source_label": "versailles", "sentence_idx": 1435}}, {"type": "Feature", "geometry": {"type": "Point", "coordinates": [-0.70312, 52.16045]}, "properties": {"source_label": "england", "sentence_idx": 1435}}, {"type": "Feature", "geometry": {"type": "Point", "coordinates": [2.0, 46.0]}, "properties": {"source_label": "frankreich", "sentence_idx": 1438}}]}