{
    "type": "FeatureCollection",
    "features": [
        {
            "type": "Feature",
            "geometry": {
                "type": "Point",
                "coordinates": [
                    9.14062,
                    48.69096
                ]
            },
            "properties": {
                "source_label": "europa",
                "geonames_label": "Europe",
                "url": "https://www.geonames.org/6255148",
                "sentence_idx": 2001
            }
        },
        {
            "type": "Feature",
            "geometry": {
                "type": "Point",
                "coordinates": [
                    -0.70312,
                    52.16045
                ]
            },
            "properties": {
                "source_label": "england",
                "geonames_label": "England",
                "url": "https://www.geonames.org/6269131",
                "sentence_idx": 2005
            }
        },
        {
            "type": "Feature",
            "geometry": {
                "type": "Point",
                "coordinates": [
                    9.14062,
                    48.69096
                ]
            },
            "properties": {
                "source_label": "europa",
                "geonames_label": "Europe",
                "url": "https://www.geonames.org/6255148",
                "sentence_idx": 2016
            }
        },
        {
            "type": "Feature",
            "geometry": {
                "type": "Point",
                "coordinates": [
                    -0.70312,
                    52.16045
                ]
            },
            "properties": {
                "source_label": "england",
                "geonames_label": "England",
                "url": "https://www.geonames.org/6269131",
                "sentence_idx": 2024
            }
        }
    ]
}