{
    "type": "FeatureCollection",
    "features": [
        {
            "type": "Feature",
            "geometry": {
                "type": "Point",
                "coordinates": [
                    2.0,
                    46.0
                ]
            },
            "properties": {
                "source_label": "frankreich",
                "geonames_label": "France",
                "url": "https://www.geonames.org/3017382",
                "sentence_idx": 1417
            }
        },
        {
            "type": "Feature",
            "geometry": {
                "type": "Point",
                "coordinates": [
                    2.0,
                    46.0
                ]
            },
            "properties": {
                "source_label": "frankreich",
                "geonames_label": "France",
                "url": "https://www.geonames.org/3017382",
                "sentence_idx": 1419
            }
        },
        {
            "type": "Feature",
            "geometry": {
                "type": "Point",
                "coordinates": [
                    2.13424,
                    48.80359
                ]
            },
            "properties": {
                "source_label": "versailles",
                "geonames_label": "Versailles",
                "url": "https://www.geonames.org/2969679",
                "sentence_idx": 1435
            }
        },
        {
            "type": "Feature",
            "geometry": {
                "type": "Point",
                "coordinates": [
                    -0.70312,
                    52.16045
                ]
            },
            "properties": {
                "source_label": "england",
                "geonames_label": "England",
                "url": "https://www.geonames.org/6269131",
                "sentence_idx": 1435
            }
        },
        {
            "type": "Feature",
            "geometry": {
                "type": "Point",
                "coordinates": [
                    2.0,
                    46.0
                ]
            },
            "properties": {
                "source_label": "frankreich",
                "geonames_label": "France",
                "url": "https://www.geonames.org/3017382",
                "sentence_idx": 1438
            }
        }
    ]
}