{"type": "FeatureCollection", "features": [{"type": "Feature", "geometry": {"type": "Point", "coordinates": [-100.54688, 46.07323]}, "properties": {"source_label": "nord amerika", "sentence_idx": 948}}, {"type": "Feature", "geometry": {"type": "Point", "coordinates": [-98.5, 39.76]}, "properties": {"source_label": "vereinigten staaten", "sentence_idx": 961}}, {"type": "Feature", "geometry": {"type": "Point", "coordinates": [-100.54688, 46.07323]}, "properties": {"source_label": "amerika", "sentence_idx": 964}}, {"type": "Feature", "geometry": {"type": "Point", "coordinates": [-100.54688, 46.07323]}, "properties": {"source_label": "amerika", "sentence_idx": 980}}, {"type": "Feature", "geometry": {"type": "Point", "coordinates": [-100.54688, 46.07323]}, "properties": {"source_label": "amerika", "sentence_idx": 982}}, {"type": "Feature", "geometry": {"type": "Point", "coordinates": [-100.54688, 46.07323]}, "properties": {"source_label": "amerika", "sentence_idx": 985}}, {"type": "Feature", "geometry": {"type": "Point", "coordinates": [-100.54688, 46.07323]}, "properties": {"source_label": "amerika", "sentence_idx": 988}}, {"type": "Feature", "geometry": {"type": "Point", "coordinates": [-100.54688, 46.07323]}, "properties": {"source_label": "amerika", "sentence_idx": 990}}, {"type": "Feature", "geometry": {"type": "Point", "coordinates": [-100.54688, 46.07323]}, "properties": {"source_label": "nord amerika", "sentence_idx": 994}}, {"type": "Feature", "geometry": {"type": "Point", "coordinates": [-100.54688, 46.07323]}, "properties": {"source_label": "nordamerika", "sentence_idx": 996}}, {"type": "Feature", "geometry": {"type": "Point", "coordinates": [-100.54688, 46.07323]}, "properties": {"source_label": "nord amerika", "sentence_idx": 996}}, {"type": "Feature", "geometry": {"type": "Point", "coordinates": [-100.54688, 46.07323]}, "properties": {"source_label": "amerika", "sentence_idx": 998}}, {"type": "Feature", "geometry": {"type": "Point", "coordinates": [-100.54688, 46.07323]}, "properties": {"source_label": "amerika", "sentence_idx": 1004}}, {"type": "Feature", "geometry": {"type": "Point", "coordinates": [-106.00085, 34.50034]}, "properties": {"source_label": "neu mexiko", "sentence_idx": 1006}}, {"type": "Feature", "geometry": {"type": "Point", "coordinates": [-92.00939, 30.12595]}, "properties": {"source_label": "louisiana", "sentence_idx": 1011}}, {"type": "Feature", "geometry": {"type": "Point", "coordinates": [-102.0, 23.0]}, "properties": {"source_label": "mexiko", "sentence_idx": 1012}}, {"type": "Feature", "geometry": {"type": "Point", "coordinates": [-100.54688, 46.07323]}, "properties": {"source_label": "nord amerika", "sentence_idx": 1013}}]}