{"type": "FeatureCollection", "features": [{"type": "Feature", "geometry": {"type": "Point", "coordinates": [-100.54688, 46.07323]}, "properties": {"source_label": "amerika", "sentence_idx": 4}}, {"type": "Feature", "geometry": {"type": "Point", "coordinates": [-100.54688, 46.07323]}, "properties": {"source_label": "nord amerika", "sentence_idx": 9}}, {"type": "Feature", "geometry": {"type": "Point", "coordinates": [-98.5, 39.76]}, "properties": {"source_label": "vereinigte staaten", "sentence_idx": 9}}, {"type": "Feature", "geometry": {"type": "Point", "coordinates": [-100.54688, 46.07323]}, "properties": {"source_label": "amerika", "sentence_idx": 22}}, {"type": "Feature", "geometry": {"type": "Point", "coordinates": [-100.54688, 46.07323]}, "properties": {"source_label": "nord amerika", "sentence_idx": 22}}, {"type": "Feature", "geometry": {"type": "Point", "coordinates": [-100.54688, 46.07323]}, "properties": {"source_label": "amerika", "sentence_idx": 27}}, {"type": "Feature", "geometry": {"type": "Point", "coordinates": [-100.54688, 46.07323]}, "properties": {"source_label": "amerika", "sentence_idx": 27}}, {"type": "Feature", "geometry": {"type": "Point", "coordinates": [-98.5, 39.76]}, "properties": {"source_label": "vereinigten staaten", "sentence_idx": 28}}, {"type": "Feature", "geometry": {"type": "Point", "coordinates": [-100.54688, 46.07323]}, "properties": {"source_label": "amerika", "sentence_idx": 29}}]}